{
 "players": [
 {
 "college": "South Carolina Gamecocks",
"current_class": null,
"current_eligible_year":     2002,
"dob": "1979-03-19",
"draft": {
 "round":        2,
"season":     2002,
"selection":       59,
"team": {
 "abbreviation": "PHI",
"city": "Philadelphia",
"id":       24,
"nickname": "Eagles",
"primary_color": "#004c54",
"secondary_color": "#a5acaf",
"slug": "philadelphia-eagles" 
},
"type": "AD" 
},
"first_name": "Sheldon",
"height":      510,
"id":     1066,
"jersey_number": "24",
"last_name": "Brown",
"position": "CB",
"speed":     4.47,
"team": {
 "abbreviation": "CLV",
"city": "Cleveland",
"id":        8,
"nickname": "Browns",
"primary_color": "#311d00",
"secondary_color": "#ff3c00",
"slug": "cleveland-browns" 
},
"weight":      200 
} 
] 
}
