{
 "players": [
 {
 "college": "Appalachian State Mountaineers",
"current_class": null,
"current_eligible_year":     2016,
"dob": "1993-01-21",
"draft": {
 "round":        5,
"season":     2016,
"selection":      142,
"team": {
 "abbreviation": "SF",
"city": "San Francisco",
"id":       28,
"nickname": "49ers",
"primary_color": "#aa0000",
"secondary_color": "#ad995d",
"slug": "san-francisco-49ers" 
},
"type": "AD" 
},
"first_name": "Ronald",
"height":      604,
"id":    10776,
"jersey_number": "98",
"last_name": "Blair III",
"position": "ED",
"speed":     5.15,
"team": {
 "abbreviation": "SF",
"city": "San Francisco",
"id":       28,
"nickname": "49ers",
"primary_color": "#aa0000",
"secondary_color": "#ad995d",
"slug": "san-francisco-49ers" 
},
"weight":      270 
} 
] 
}
