{
 "players": [
 {
 "college": "Clemson Tigers",
"current_class": null,
"current_eligible_year":     2016,
"dob": "1994-02-11",
"draft": {
 "round":        7,
"season":     2016,
"selection":      244,
"team": {
 "abbreviation": "MIN",
"city": "Minnesota",
"id":       18,
"nickname": "Vikings",
"primary_color": "#4f2683",
"secondary_color": "#ffc62f",
"slug": "minnesota-vikings" 
},
"type": "AD" 
},
"first_name": "Jayron",
"height":      604,
"id":    10878,
"jersey_number": "00",
"last_name": "Kearse",
"position": "S",
"speed":     4.62,
"team": {
 "abbreviation": "BLT",
"city": "Baltimore",
"id":        3,
"nickname": "Ravens",
"primary_color": "#1a195f",
"secondary_color": "#000000",
"slug": "baltimore-ravens" 
},
"weight":      215 
} 
] 
}
