{
 "players": [
 {
 "college": "Auburn Tigers",
"current_class": null,
"current_eligible_year":     2016,
"dob": "1994-06-23",
"draft": {
 "round": null,
"season":     2016,
"selection": null,
"team": {
 "abbreviation": "TB",
"city": "Tampa Bay",
"id":       30,
"nickname": "Buccaneers",
"primary_color": "#d50a0a",
"secondary_color": "#34302b",
"slug": "tampa-bay-buccaneers" 
},
"type": "FA" 
},
"first_name": "DaVonte",
"height":      601,
"id":    10937,
"jersey_number": "96",
"last_name": "Lambert",
"position": "DI",
"speed": null,
"team": {
 "abbreviation": "CAR",
"city": "Carolina",
"id":        5,
"nickname": "Panthers",
"primary_color": "#0085ca",
"secondary_color": "#bfc0bf",
"slug": "carolina-panthers" 
},
"weight":      279 
} 
] 
}
