{
 "players": [
 {
 "college": "Florida State Seminoles",
"current_class": null,
"current_eligible_year":     1997,
"dob": "1974-10-28",
"draft": {
 "round":        4,
"season":     1997,
"selection":      100,
"team": {
 "abbreviation": "ATL",
"city": "Atlanta",
"id":        2,
"nickname": "Falcons",
"primary_color": "#a71930",
"secondary_color": "#000000",
"slug": "atlanta-falcons" 
},
"type": "AD" 
},
"first_name": "Henry",
"height":      602,
"id":    11693,
"jersey_number": "94",
"last_name": "Crockett",
"position": "LB",
"speed": null,
"team": {
 "abbreviation": "ATL",
"city": "Atlanta",
"id":        2,
"nickname": "Falcons",
"primary_color": "#a71930",
"secondary_color": "#000000",
"slug": "atlanta-falcons" 
},
"weight":      238 
} 
] 
}
