{
 "players": [
 {
 "college": "TCU Horned Frogs",
"current_class": null,
"current_eligible_year":     2017,
"dob": "1994-04-19",
"draft": {
 "round":        7,
"season":     2017,
"selection":      227,
"team": {
 "abbreviation": "TEN",
"city": "Tennessee",
"id":       31,
"nickname": "Titans",
"primary_color": "#0c2340",
"secondary_color": "#418fde",
"slug": "tennessee-titans" 
},
"type": "AD" 
},
"first_name": "Josh",
"height":      603,
"id":    11982,
"jersey_number": "42",
"last_name": "Carraway",
"position": "ED",
"speed":     4.74,
"team": {
 "abbreviation": "LA",
"city": "Los Angeles",
"id":       26,
"nickname": "Rams",
"primary_color": "#003594",
"secondary_color": "#ffd100",
"slug": "los-angeles-rams" 
},
"weight":      242 
} 
] 
}
