{
 "players": [
 {
 "college": "Toledo Rockets",
"current_class": null,
"current_eligible_year":     2017,
"dob": "1992-09-21",
"draft": {
 "round":        7,
"season":     2017,
"selection":      244,
"team": {
 "abbreviation": "OAK",
"city": "Oakland",
"id":       23,
"nickname": "Raiders",
"primary_color": "#000000",
"secondary_color": "#a5acaf",
"slug": "oakland-raiders" 
},
"type": "AD" 
},
"first_name": "Treyvon",
"height":      602,
"id":    11999,
"jersey_number": "00",
"last_name": "Hester",
"position": "DI",
"speed": null,
"team": {
 "abbreviation": "PHI",
"city": "Philadelphia",
"id":       24,
"nickname": "Eagles",
"primary_color": "#004c54",
"secondary_color": "#a5acaf",
"slug": "philadelphia-eagles" 
},
"weight":      304 
} 
] 
}
