{
 "players": [
 {
 "college": "UCLA Bruins",
"current_class": null,
"current_eligible_year":     2017,
"dob": "1994-04-01",
"draft": {
 "round": null,
"season":     2017,
"selection": null,
"team": {
 "abbreviation": "JAX",
"city": "Jacksonville",
"id":       15,
"nickname": "Jaguars",
"primary_color": "#006778",
"secondary_color": "#d7a22a",
"slug": "jacksonville-jaguars" 
},
"type": "FA" 
},
"first_name": "Kenneth",
"height":      510,
"id":    12035,
"jersey_number": "86",
"last_name": "Walker III",
"position": "WR",
"speed": null,
"team": {
 "abbreviation": "JAX",
"city": "Jacksonville",
"id":       15,
"nickname": "Jaguars",
"primary_color": "#006778",
"secondary_color": "#d7a22a",
"slug": "jacksonville-jaguars" 
},
"weight":      189 
} 
] 
}
