{
 "players": [
 {
 "college": "Michigan Wolverines",
"current_class": null,
"current_eligible_year":     2003,
"dob": "1980-02-03",
"draft": {
 "round":        2,
"season":     2003,
"selection":       53,
"team": {
 "abbreviation": "NYJ",
"city": "New York",
"id":       22,
"nickname": "Jets",
"primary_color": "#125740",
"secondary_color": "#ffffff",
"slug": "new-york-jets" 
},
"type": "AD" 
},
"first_name": "Victor",
"height":      600,
"id":     1368,
"jersey_number": "57",
"last_name": "Hobson",
"position": "LB",
"speed":     4.86,
"team": {
 "abbreviation": "ARZ",
"city": "Arizona",
"id":        1,
"nickname": "Cardinals",
"primary_color": "#97233f",
"secondary_color": "#ffffff",
"slug": "arizona-cardinals" 
},
"weight":      252 
} 
] 
}
