{
 "players": [
 {
 "college": "Cincinnati Bearcats",
"current_class": null,
"current_eligible_year":     2003,
"dob": "1979-10-29",
"draft": {
 "round":        3,
"season":     2003,
"selection":       67,
"team": {
 "abbreviation": "HST",
"city": "Houston",
"id":       13,
"nickname": "Texans",
"primary_color": "#03202f",
"secondary_color": "#a71930",
"slug": "houston-texans" 
},
"type": "AD" 
},
"first_name": "Antwan",
"height":      603,
"id":     1382,
"jersey_number": "56",
"last_name": "Peek",
"position": "ED",
"speed":     4.65,
"team": {
 "abbreviation": "CLV",
"city": "Cleveland",
"id":        8,
"nickname": "Browns",
"primary_color": "#311d00",
"secondary_color": "#ff3c00",
"slug": "cleveland-browns" 
},
"weight":      250 
} 
] 
}
