{
 "players": [
 {
 "college": "Navy Midshipmen",
"current_class": null,
"current_eligible_year":     2005,
"dob": "1981-12-30",
"draft": {
 "round": null,
"season":     2005,
"selection": null,
"team": {
 "abbreviation": "NE",
"city": "New England",
"id":       19,
"nickname": "Patriots",
"primary_color": "#002244",
"secondary_color": "#c60c30",
"slug": "new-england-patriots" 
},
"type": "FA" 
},
"first_name": "Kyle",
"height":      511,
"id":     2574,
"jersey_number": "36",
"last_name": "Eckel",
"position": "FB",
"speed":     4.84,
"team": {
 "abbreviation": "NO",
"city": "New Orleans",
"id":       20,
"nickname": "Saints",
"primary_color": "#d3bc8d",
"secondary_color": "#000000",
"slug": "new-orleans-saints" 
},
"weight":      244 
} 
] 
}
