{
 "players": [
 {
 "college": "Lafayette Leopards",
"current_class": null,
"current_eligible_year":     2006,
"dob": "1984-04-14",
"draft": {
 "round": null,
"season":     2006,
"selection": null,
"team": {
 "abbreviation": "NYJ",
"city": "New York",
"id":       22,
"nickname": "Jets",
"primary_color": "#125740",
"secondary_color": "#ffffff",
"slug": "new-york-jets" 
},
"type": "FA" 
},
"first_name": "Blake",
"height":      601,
"id":     3278,
"jersey_number": "56",
"last_name": "Costanzo",
"position": "LB",
"speed": null,
"team": {
 "abbreviation": "SF",
"city": "San Francisco",
"id":       28,
"nickname": "49ers",
"primary_color": "#aa0000",
"secondary_color": "#ad995d",
"slug": "san-francisco-49ers" 
},
"weight":      235 
} 
] 
}
