{
 "players": [
 {
 "college": "North Carolina State Wolfpack",
"current_class": null,
"current_eligible_year":     2007,
"dob": "1984-06-06",
"draft": {
 "round":        4,
"season":     2007,
"selection":      115,
"team": {
 "abbreviation": "TEN",
"city": "Tennessee",
"id":       31,
"nickname": "Titans",
"primary_color": "#0c2340",
"secondary_color": "#418fde",
"slug": "tennessee-titans" 
},
"type": "AD" 
},
"first_name": "Leroy",
"height":      602,
"id":     3731,
"jersey_number": "64",
"last_name": "Harris",
"position": "G",
"speed":     5.35,
"team": {
 "abbreviation": "DET",
"city": "Detroit",
"id":       11,
"nickname": "Lions",
"primary_color": "#0076b6",
"secondary_color": "#b0b7bc",
"slug": "detroit-lions" 
},
"weight":      298 
} 
] 
}
