{
 "players": [
 {
 "college": "Virginia Cavaliers",
"current_class": null,
"current_eligible_year":     2008,
"dob": "1984-11-04",
"draft": {
 "round":        1,
"season":     2008,
"selection":       15,
"team": {
 "abbreviation": "KC",
"city": "Kansas City",
"id":       16,
"nickname": "Chiefs",
"primary_color": "#e31837",
"secondary_color": "#ffb81c",
"slug": "kansas-city-chiefs" 
},
"type": "AD" 
},
"first_name": "Branden",
"height":      606,
"id":     4329,
"jersey_number": "76",
"last_name": "Albert",
"position": "T",
"speed":     5.17,
"team": {
 "abbreviation": "JAX",
"city": "Jacksonville",
"id":       15,
"nickname": "Jaguars",
"primary_color": "#006778",
"secondary_color": "#d7a22a",
"slug": "jacksonville-jaguars" 
},
"weight":      309 
} 
] 
}
