{
 "players": [
 {
 "college": "Texas A&M Aggies",
"current_class": null,
"current_eligible_year":     2019,
"dob": "1996-09-26",
"draft": {
 "round":        5,
"season":     2019,
"selection":      150,
"team": {
 "abbreviation": "GB",
"city": "Green Bay",
"id":       12,
"nickname": "Packers",
"primary_color": "#183028",
"secondary_color": "#ffb81c",
"slug": "green-bay-packers" 
},
"type": "AD" 
},
"first_name": "Kingsley",
"height":      603,
"id":    48718,
"jersey_number": "96",
"last_name": "Keke",
"position": "DI",
"speed": null,
"team": {
 "abbreviation": "GB",
"city": "Green Bay",
"id":       12,
"nickname": "Packers",
"primary_color": "#183028",
"secondary_color": "#ffb81c",
"slug": "green-bay-packers" 
},
"weight":      288 
} 
] 
}
