{
 "players": [
 {
 "college": "Utah Utes",
"current_class": null,
"current_eligible_year":     2010,
"dob": "1987-03-22",
"draft": {
 "round":        5,
"season":     2010,
"selection":      156,
"team": {
 "abbreviation": "BLT",
"city": "Baltimore",
"id":        3,
"nickname": "Ravens",
"primary_color": "#1a195f",
"secondary_color": "#000000",
"slug": "baltimore-ravens" 
},
"type": "AD" 
},
"first_name": "David",
"height":      600,
"id":     5679,
"jersey_number": "10",
"last_name": "Reed",
"position": "WR",
"speed":     4.56,
"team": {
 "abbreviation": "SF",
"city": "San Francisco",
"id":       28,
"nickname": "49ers",
"primary_color": "#aa0000",
"secondary_color": "#ad995d",
"slug": "san-francisco-49ers" 
},
"weight":      190 
} 
] 
}
