{
 "players": [
 {
 "college": "Southern Utah Thunderbirds",
"current_class": null,
"current_eligible_year":     2019,
"dob": "1996-09-19",
"draft": {
 "round": null,
"season":     2019,
"selection": null,
"team": {
 "abbreviation": "CHI",
"city": "Chicago",
"id":        6,
"nickname": "Bears",
"primary_color": "#0b162a",
"secondary_color": "#c83803",
"slug": "chicago-bears" 
},
"type": "FA" 
},
"first_name": "Marquez",
"height":      604,
"id":    60087,
"jersey_number": "O71",
"last_name": "Tucker",
"position": "G",
"speed": null,
"team": {
 "abbreviation": "CHI",
"city": "Chicago",
"id":        6,
"nickname": "Bears",
"primary_color": "#0b162a",
"secondary_color": "#c83803",
"slug": "chicago-bears" 
},
"weight":      300 
} 
] 
}
