{
 "players": [
 {
 "college": "California Golden Bears",
"current_class": null,
"current_eligible_year":     2012,
"dob": "1990-03-12",
"draft": {
 "round":        5,
"season":     2012,
"selection":      166,
"team": {
 "abbreviation": "CIN",
"city": "Cincinnati",
"id":        7,
"nickname": "Bengals",
"primary_color": "#fb4f14",
"secondary_color": "#000000",
"slug": "cincinnati-bengals" 
},
"type": "AD" 
},
"first_name": "Marvin",
"height":      602,
"id":     7158,
"jersey_number": "11",
"last_name": "Jones Jr.",
"position": "WR",
"speed":     4.46,
"team": {
 "abbreviation": "DET",
"city": "Detroit",
"id":       11,
"nickname": "Lions",
"primary_color": "#0076b6",
"secondary_color": "#b0b7bc",
"slug": "detroit-lions" 
},
"weight":      198 
} 
] 
}
