{
 "players": [
 {
 "college": "Kansas State Wildcats",
"current_class": null,
"current_eligible_year":     2015,
"dob": "1992-09-28",
"draft": {
 "round":        3,
"season":     2015,
"selection":       69,
"team": {
 "abbreviation": "SEA",
"city": "Seattle",
"id":       29,
"nickname": "Seahawks",
"primary_color": "#002244",
"secondary_color": "#69be28",
"slug": "seattle-seahawks" 
},
"type": "AD" 
},
"first_name": "Tyler",
"height":      510,
"id":     9502,
"jersey_number": "16",
"last_name": "Lockett",
"position": "WR",
"speed":      4.4,
"team": {
 "abbreviation": "SEA",
"city": "Seattle",
"id":       29,
"nickname": "Seahawks",
"primary_color": "#002244",
"secondary_color": "#69be28",
"slug": "seattle-seahawks" 
},
"weight":      182 
} 
] 
}
