{
 "defense_summary": {
 "subject": {
 "eligible": "defense",
"grade_keys": [ "defense", "defense_penalty", "run_defense", "pass_rush_defense", "coverage_defense", "tackle" ],
"league_id":        1,
"player_id":     5659,
"roster": "defense",
"season":     2011,
"secondary": false,
"week": [] 
},
"week_totals": [
 {
 "assists":        5,
"forced_fumbles":        1,
"franchise_id":       16,
"hits":        0,
"interceptions":        3,
"league_id":        1,
"pass_break_ups":        7,
"player_game_count":       16,
"sacks":        0,
"season":     2011,
"season_id":     2011,
"tackles":       50,
"team_name": "KC" 
} 
],
"weeks": [
 {
 "assists":        0,
"away_franchise_id":        4,
"away_team_name": "BUF",
"forced_fumbles":        0,
"game": {
 "away_franchise_id":        4,
"away_team_name": "BUF",
"game_id":     2065,
"home_franchise_id":       16,
"home_team_name": "KC",
"player_franchise_id":       16,
"position": "FS",
"status": "S",
"week":        1 
},
"game_id":     2065,
"hits":        0,
"home_franchise_id":       16,
"home_team_name": "KC",
"interceptions":        0,
"jersey_number": "23",
"pass_break_ups":        0,
"player_franchise_id":       16,
"player_id":     5659,
"position": "FS",
"sacks":        0,
"status": "S",
"tackles":        4,
"week":        1 
},
{
 "assists":        0,
"away_franchise_id":       16,
"away_team_name": "KC",
"forced_fumbles":        0,
"game": {
 "away_franchise_id":       16,
"away_team_name": "KC",
"game_id":     2081,
"home_franchise_id":       11,
"home_team_name": "DET",
"player_franchise_id":       16,
"position": "FS",
"status": "S",
"week":        2 
},
"game_id":     2081,
"hits":        0,
"home_franchise_id":       11,
"home_team_name": "DET",
"interceptions":        0,
"jersey_number": "23",
"pass_break_ups":        0,
"player_franchise_id":       16,
"player_id":     5659,
"position": "FS",
"sacks":        0,
"status": "S",
"tackles":        5,
"week":        2 
},
{
 "assists":        0,
"away_franchise_id":       16,
"away_team_name": "KC",
"forced_fumbles":        0,
"game": {
 "away_franchise_id":       16,
"away_team_name": "KC",
"game_id":     2095,
"home_franchise_id":       27,
"home_team_name": "SD",
"player_franchise_id":       16,
"position": "FS",
"status": "S",
"week":        3 
},
"game_id":     2095,
"hits":        0,
"home_franchise_id":       27,
"home_team_name": "SD",
"interceptions":        1,
"jersey_number": "23",
"pass_break_ups":        0,
"player_franchise_id":       16,
"player_id":     5659,
"position": "FS",
"sacks":        0,
"status": "S",
"tackles":        2,
"week":        3 
},
{
 "assists":        0,
"away_franchise_id":       18,
"away_team_name": "MIN",
"forced_fumbles":        0,
"game": {
 "away_franchise_id":       18,
"away_team_name": "MIN",
"game_id":     2111,
"home_franchise_id":       16,
"home_team_name": "KC",
"player_franchise_id":       16,
"position": "FS",
"status": "S",
"week":        4 
},
"game_id":     2111,
"hits":        0,
"home_franchise_id":       16,
"home_team_name": "KC",
"interceptions":        0,
"jersey_number": "23",
"pass_break_ups":        0,
"player_franchise_id":       16,
"player_id":     5659,
"position": "FS",
"sacks":        0,
"status": "S",
"tackles":        4,
"week":        4 
},
{
 "assists":        1,
"away_franchise_id":       16,
"away_team_name": "KC",
"forced_fumbles":        0,
"game": {
 "away_franchise_id":       16,
"away_team_name": "KC",
"game_id":     2125,
"home_franchise_id":       14,
"home_team_name": "IND",
"player_franchise_id":       16,
"position": "FS",
"status": "S",
"week":        5 
},
"game_id":     2125,
"hits":        0,
"home_franchise_id":       14,
"home_team_name": "IND",
"interceptions":        0,
"jersey_number": "23",
"pass_break_ups":        0,
"player_franchise_id":       16,
"player_id":     5659,
"position": "FS",
"sacks":        0,
"status": "S",
"tackles":        2,
"week":        5 
},
{
 "assists":        1,
"away_franchise_id":       16,
"away_team_name": "KC",
"forced_fumbles":        0,
"game": {
 "away_franchise_id":       16,
"away_team_name": "KC",
"game_id":     2156,
"home_franchise_id":       23,
"home_team_name": "OAK",
"player_franchise_id":       16,
"position": "FS",
"status": "S",
"week":        7 
},
"game_id":     2156,
"hits":        0,
"home_franchise_id":       23,
"home_team_name": "OAK",
"interceptions":        1,
"jersey_number": "23",
"pass_break_ups":        0,
"player_franchise_id":       16,
"player_id":     5659,
"position": "FS",
"sacks":        0,
"status": "S",
"tackles":        2,
"week":        7 
},
{
 "assists":        0,
"away_franchise_id":       27,
"away_team_name": "SD",
"forced_fumbles":        0,
"game": {
 "away_franchise_id":       27,
"away_team_name": "SD",
"game_id":     2173,
"home_franchise_id":       16,
"home_team_name": "KC",
"player_franchise_id":       16,
"position": "FS",
"status": "S",
"week":        8 
},
"game_id":     2173,
"hits":        0,
"home_franchise_id":       16,
"home_team_name": "KC",
"interceptions":        1,
"jersey_number": "23",
"pass_break_ups":        0,
"player_franchise_id":       16,
"player_id":     5659,
"position": "FS",
"sacks":        0,
"status": "S",
"tackles":        1,
"week":        8 
},
{
 "assists":        0,
"away_franchise_id":       17,
"away_team_name": "MIA",
"forced_fumbles":        0,
"game": {
 "away_franchise_id":       17,
"away_team_name": "MIA",
"game_id":     2177,
"home_franchise_id":       16,
"home_team_name": "KC",
"player_franchise_id":       16,
"position": "FS",
"status": "S",
"week":        9 
},
"game_id":     2177,
"hits":        0,
"home_franchise_id":       16,
"home_team_name": "KC",
"interceptions":        0,
"jersey_number": "23",
"pass_break_ups":        1,
"player_franchise_id":       16,
"player_id":     5659,
"position": "FS",
"sacks":        0,
"status": "S",
"tackles":        3,
"week":        9 
},
{
 "assists":        0,
"away_franchise_id":       10,
"away_team_name": "DEN",
"forced_fumbles":        0,
"game": {
 "away_franchise_id":       10,
"away_team_name": "DEN",
"game_id":     2194,
"home_franchise_id":       16,
"home_team_name": "KC",
"player_franchise_id":       16,
"position": "FS",
"status": "S",
"week":       10 
},
"game_id":     2194,
"hits":        0,
"home_franchise_id":       16,
"home_team_name": "KC",
"interceptions":        0,
"jersey_number": "23",
"pass_break_ups":        2,
"player_franchise_id":       16,
"player_id":     5659,
"position": "FS",
"sacks":        0,
"status": "S",
"tackles":        4,
"week":       10 
},
{
 "assists":        0,
"away_franchise_id":       16,
"away_team_name": "KC",
"forced_fumbles":        0,
"game": {
 "away_franchise_id":       16,
"away_team_name": "KC",
"game_id":     2217,
"home_franchise_id":       19,
"home_team_name": "NE",
"player_franchise_id":       16,
"position": "FS",
"status": "S",
"week":       11 
},
"game_id":     2217,
"hits":        0,
"home_franchise_id":       19,
"home_team_name": "NE",
"interceptions":        0,
"jersey_number": "23",
"pass_break_ups":        0,
"player_franchise_id":       16,
"player_id":     5659,
"position": "FS",
"sacks":        0,
"status": "S",
"tackles":        2,
"week":       11 
},
{
 "assists":        1,
"away_franchise_id":       25,
"away_team_name": "PIT",
"forced_fumbles":        0,
"game": {
 "away_franchise_id":       25,
"away_team_name": "PIT",
"game_id":     2223,
"home_franchise_id":       16,
"home_team_name": "KC",
"player_franchise_id":       16,
"position": "FS",
"status": "S",
"week":       12 
},
"game_id":     2223,
"hits":        0,
"home_franchise_id":       16,
"home_team_name": "KC",
"interceptions":        0,
"jersey_number": "23",
"pass_break_ups":        0,
"player_franchise_id":       16,
"player_id":     5659,
"position": "FS",
"sacks":        0,
"status": "S",
"tackles":        2,
"week":       12 
},
{
 "assists":        1,
"away_franchise_id":       16,
"away_team_name": "KC",
"forced_fumbles":        0,
"game": {
 "away_franchise_id":       16,
"away_team_name": "KC",
"game_id":     2236,
"home_franchise_id":        6,
"home_team_name": "CHI",
"player_franchise_id":       16,
"position": "FS",
"status": "S",
"week":       13 
},
"game_id":     2236,
"hits":        0,
"home_franchise_id":        6,
"home_team_name": "CHI",
"interceptions":        0,
"jersey_number": "23",
"pass_break_ups":        1,
"player_franchise_id":       16,
"player_id":     5659,
"position": "FS",
"sacks":        0,
"status": "S",
"tackles":        4,
"week":       13 
},
{
 "assists":        1,
"away_franchise_id":       16,
"away_team_name": "KC",
"forced_fumbles":        0,
"game": {
 "away_franchise_id":       16,
"away_team_name": "KC",
"game_id":     2258,
"home_franchise_id":       22,
"home_team_name": "NYJ",
"player_franchise_id":       16,
"position": "FS",
"status": "S",
"week":       14 
},
"game_id":     2258,
"hits":        0,
"home_franchise_id":       22,
"home_team_name": "NYJ",
"interceptions":        0,
"jersey_number": "23",
"pass_break_ups":        0,
"player_franchise_id":       16,
"player_id":     5659,
"position": "FS",
"sacks":        0,
"status": "S",
"tackles":        6,
"week":       14 
},
{
 "assists":        0,
"away_franchise_id":       12,
"away_team_name": "GB",
"forced_fumbles":        0,
"game": {
 "away_franchise_id":       12,
"away_team_name": "GB",
"game_id":     2273,
"home_franchise_id":       16,
"home_team_name": "KC",
"player_franchise_id":       16,
"position": "FS",
"status": "S",
"week":       15 
},
"game_id":     2273,
"hits":        0,
"home_franchise_id":       16,
"home_team_name": "KC",
"interceptions":        0,
"jersey_number": "23",
"pass_break_ups":        1,
"player_franchise_id":       16,
"player_id":     5659,
"position": "FS",
"sacks":        0,
"status": "S",
"tackles":        2,
"week":       15 
},
{
 "assists":        0,
"away_franchise_id":       23,
"away_team_name": "OAK",
"forced_fumbles":        0,
"game": {
 "away_franchise_id":       23,
"away_team_name": "OAK",
"game_id":     2285,
"home_franchise_id":       16,
"home_team_name": "KC",
"player_franchise_id":       16,
"position": "FS",
"status": "S",
"week":       16 
},
"game_id":     2285,
"hits":        0,
"home_franchise_id":       16,
"home_team_name": "KC",
"interceptions":        0,
"jersey_number": "23",
"pass_break_ups":        2,
"player_franchise_id":       16,
"player_id":     5659,
"position": "FS",
"sacks":        0,
"status": "S",
"tackles":        4,
"week":       16 
},
{
 "assists":        0,
"away_franchise_id":       16,
"away_team_name": "KC",
"forced_fumbles":        1,
"game": {
 "away_franchise_id":       16,
"away_team_name": "KC",
"game_id":     2299,
"home_franchise_id":       10,
"home_team_name": "DEN",
"player_franchise_id":       16,
"position": "FS",
"status": "S",
"week":       17 
},
"game_id":     2299,
"hits":        0,
"home_franchise_id":       10,
"home_team_name": "DEN",
"interceptions":        0,
"jersey_number": "23",
"pass_break_ups":        0,
"player_franchise_id":       16,
"player_id":     5659,
"position": "FS",
"sacks":        0,
"status": "S",
"tackles":        3,
"week":       17 
} 
] 
},
"restricted": [ "first_downs", "penalties", "declined_penalties", "grades", "snap_counts", "batted_passes", "catch_rate", "hurries", "longest", "missed_tackles", "qb_rating_against", "receptions", "stops", "targets", "total_pressures", "touchdowns", "yards", "yards_after_catch", "yards_per_reception" ] 
}
